README.md
setup.py
examples/__init__.py
examples/load_file.py
examples/customwf/__init__.py
examples/example1/__init__.py
examples/iris/__init__.py
jupyter/__init__.py
makeup/__init__.py
makeup/__main__.py
makeup/bootstrap.py
makeup/delegate.py
makeup/deps.py
makeup/models.py
makeup/url_cache.py
makeup.egg-info/PKG-INFO
makeup.egg-info/SOURCES.txt
makeup.egg-info/dependency_links.txt
makeup.egg-info/top_level.txt
makeup/urlregistry/__init__.py
makeup/urlregistry/sqlite.py
makeup/view/__init__.py
test/test_deps.py
test/test_features.py
test/test_load.py
test/test_load_url.py
test/test_pickle.py
test/test_sqlitehandler.py
test/test_train.py
test/test_url_cache.py
test/test_urlregistry.py
test/test_workflow.py