Metadata-Version: 2.1
Name: makeup
Version: 0.1.3
Summary: Make your models look pretty.
Home-page: https://github.com/trevorgrayson/mlf
Author: trevor grayson
Author-email: trevor@dave.com
License: UNKNOWN
Keywords: machine learning,data science,make,models
Platform: UNKNOWN
